{
  "scopus": {
    "works": 24,
    "citations": 78,
    "hindex": 4,
    "url": "https://www.scopus.com/authid/detail.uri?authorId=57193428877"
  },
  "wos": {
    "works": 25,
    "citations": 154,
    "hindex": 6,
    "url": "https://www.webofscience.com/wos/author/record/AAU-8923-2021"
  },
  "scholar": {
    "works": 20,
    "citations": 622,
    "hindex": 12,
    "url": "https://scholar.google.es/citations?user=5QO7XHYAAAAJ"
  },
  "orcid": {
    "works": 25,
    "url": "https://orcid.org/0000-0001-6526-7740"
  },
  "updated": "2026-07-17"
}